__init__.py
8x_esystem_app_drivers_location_api_python_sdk-1.1.0.dist-info/licenses/LICENSE
oitoxesystem/__init__.py
oitoxesystem/appdriverslocationapi/__init__.py
oitoxesystem/appdriverslocationapi/api.py
oitoxesystem/appdriverslocationapi/apis/__init__.py
oitoxesystem/appdriverslocationapi/apis/vehicles.py
8x_esystem_app_drivers_location_api_python_sdk-1.1.0.dist-info/METADATA
8x_esystem_app_drivers_location_api_python_sdk-1.1.0.dist-info/WHEEL
8x_esystem_app_drivers_location_api_python_sdk-1.1.0.dist-info/top_level.txt
8x_esystem_app_drivers_location_api_python_sdk-1.1.0.dist-info/RECORD
